django_otel_smtp_backend/__init__.py
django_otel_smtp_backend/backend.py
django_otel_smtp_backend-0.0.4.dist-info/LICENSE
django_otel_smtp_backend-0.0.4.dist-info/METADATA
django_otel_smtp_backend-0.0.4.dist-info/WHEEL
django_otel_smtp_backend-0.0.4.dist-info/top_level.txt
django_otel_smtp_backend-0.0.4.dist-info/RECORD
