Metadata-Version: 2.1
Name: django-otel-smtp-backend
Version: 0.0.4
Summary: Wraps the default Django SMTP Email Backend with trace instrumentation to the OpenTelemetry
Author-email: Eduardo Oliveira <eduardo_y05@outlook.com>
Maintainer-email: Eduardo Oliveira <eduardo_y05@outlook.com>
License: MIT License
Project-URL: homepage, https://github.com/inventare/django-otel-smtp-backend
Project-URL: documentation, https://github.com/inventare/django-otel-smtp-backend
Keywords: django,email,mail,smtp,open-telemetry,telemetry,otel
Classifier: Development Status :: 5 - Production/Stable
Classifier: Environment :: Web Environment
Classifier: Framework :: Django
Classifier: Intended Audience :: Developers
Classifier: License :: OSI Approved :: MIT License
Classifier: Operating System :: OS Independent
Classifier: Programming Language :: Python
Classifier: Programming Language :: Python :: 3
Classifier: Programming Language :: Python :: 3.8
Classifier: Programming Language :: Python :: 3.9
Classifier: Programming Language :: Python :: 3.10
Classifier: Programming Language :: Python :: 3.11
Classifier: Programming Language :: Python :: 3.12
Requires-Python: >=3.8
License-File: LICENSE
Requires-Dist: django >=4.2
Requires-Dist: opentelemetry-api
Provides-Extra: dev
Requires-Dist: black ; extra == 'dev'
Requires-Dist: isort ; extra == 'dev'
Requires-Dist: pre-commit ; extra == 'dev'
